{
  "resultCount": 1,
  "results": [
    {
      "date": "20260701",
      "country": "us",
      "mediaType": "podcasts",
      "feed": "top-podcast-episodes",
      "rank": 100,
      "artistName": "Hank Smith & John Bytheway",
      "id": "1000776913335",
      "name": "2 Chronicles 14-20; 26; 30 Part 1 • Sister Heather Farrell • July 20-26 • Come, Follow Me",
      "kind": "podcast-episodes",
      "artworkUrl100": "https://is1-ssl.mzstatic.com/image/thumb/Podcasts211/v4/17/9f/25/179f250b-0374-d871-35df-428961fe49a4/mza_580844241288958844.jpg/100x100bb.png",
      "genres": [
        {
          "name": "Christianity"
        }
      ],
      "url": "https://podcasts.apple.com/us/podcast/2-chronicles-14-20-26-30-part-1-sister-heather-farrell/id1545433056?i=1000776913335"
    }
  ]
}
