{
  "resultCount": 4,
  "results": [
    {
      "date": "20260406",
      "country": "us",
      "mediaType": "music",
      "feed": "top-albums",
      "rank": 49,
      "artistName": "Silent Chills",
      "id": "1542331034",
      "name": "Rain Sounds For Sleep",
      "releaseDate": "2020-12-11",
      "kind": "albums",
      "artistId": "1493554874",
      "artistUrl": "https://music.apple.com/us/artist/silent-chills/1493554874",
      "artworkUrl100": "https://is1-ssl.mzstatic.com/image/thumb/Music211/v4/29/89/2f/29892f37-c23c-5d72-f6e2-09619149b3b3/cover_4062851942317.jpg/100x100bb.jpg",
      "genres": [
        {
          "genreId": "34",
          "name": "Music",
          "url": "https://itunes.apple.com/us/genre/id34"
        }
      ],
      "url": "https://music.apple.com/us/album/rain-sounds-for-sleep/1542331034"
    },
    {
      "date": "20260501",
      "country": "us",
      "mediaType": "music",
      "feed": "top-albums",
      "rank": 65,
      "artistName": "Silent Chills",
      "id": "1542331034",
      "name": "Rain Sounds For Sleep",
      "releaseDate": "2020-12-11",
      "kind": "albums",
      "artistId": "1493554874",
      "artistUrl": "https://music.apple.com/us/artist/silent-chills/1493554874",
      "artworkUrl100": "https://is1-ssl.mzstatic.com/image/thumb/Music211/v4/29/89/2f/29892f37-c23c-5d72-f6e2-09619149b3b3/cover_4062851942317.jpg/100x100bb.jpg",
      "genres": [
        {
          "genreId": "34",
          "name": "Music",
          "url": "https://itunes.apple.com/us/genre/id34"
        }
      ],
      "url": "https://music.apple.com/us/album/rain-sounds-for-sleep/1542331034"
    },
    {
      "date": "20260601",
      "country": "us",
      "mediaType": "music",
      "feed": "top-albums",
      "rank": 62,
      "artistName": "Silent Chills",
      "id": "1542331034",
      "name": "Rain Sounds For Sleep",
      "releaseDate": "2020-12-11",
      "kind": "albums",
      "artistId": "1493554874",
      "artistUrl": "https://music.apple.com/us/artist/silent-chills/1493554874",
      "artworkUrl100": "https://is1-ssl.mzstatic.com/image/thumb/Music211/v4/29/89/2f/29892f37-c23c-5d72-f6e2-09619149b3b3/cover_4062851942317.jpg/100x100bb.jpg",
      "genres": [
        {
          "genreId": "34",
          "name": "Music",
          "url": "https://itunes.apple.com/us/genre/id34"
        }
      ],
      "url": "https://music.apple.com/us/album/rain-sounds-for-sleep/1542331034"
    },
    {
      "date": "20260701",
      "country": "us",
      "mediaType": "music",
      "feed": "top-albums",
      "rank": 38,
      "artistName": "Silent Chills",
      "id": "1542331034",
      "name": "Rain Sounds For Sleep",
      "releaseDate": "2020-12-11",
      "kind": "albums",
      "artistId": "1493554874",
      "artistUrl": "https://music.apple.com/us/artist/silent-chills/1493554874",
      "artworkUrl100": "https://is1-ssl.mzstatic.com/image/thumb/Music211/v4/29/89/2f/29892f37-c23c-5d72-f6e2-09619149b3b3/cover_4062851942317.jpg/100x100bb.jpg",
      "genres": [
        {
          "genreId": "34",
          "name": "Music",
          "url": "https://itunes.apple.com/us/genre/id34"
        }
      ],
      "url": "https://music.apple.com/us/album/rain-sounds-for-sleep/1542331034"
    }
  ]
}
