{
  "resultCount": 1,
  "results": [
    {
      "date": "20260601",
      "country": "us",
      "mediaType": "audio-books",
      "feed": "top-audio-books",
      "rank": 20,
      "artistName": "Riley Sager",
      "id": "1770922621",
      "name": "With a Vengeance: A Novel (Unabridged)",
      "releaseDate": "2025-06-10",
      "kind": "audio-books",
      "artistId": "1167845991",
      "artistUrl": "https://books.apple.com/us/author/riley-sager/id1167845991",
      "artworkUrl100": "https://is1-ssl.mzstatic.com/image/thumb/Music221/v4/85/03/80/85038083-de48-6840-ea64-6a558579d628/9798217076956.d.jpg/100x100bb.png",
      "genres": [
        {
          "genreId": "50000051",
          "name": "Mysteries & Thrillers",
          "url": "https://itunes.apple.com/us/genre/id50000051"
        },
        {
          "genreId": "50000024",
          "name": "Audiobooks",
          "url": "https://itunes.apple.com/us/genre/id50000024"
        },
        {
          "genreId": "50000040",
          "name": "Fiction",
          "url": "https://itunes.apple.com/us/genre/id50000040"
        }
      ],
      "url": "https://books.apple.com/us/audiobook/with-a-vengeance-a-novel-unabridged/id1770922621"
    }
  ]
}
