{
  "resultCount": 1,
  "results": [
    {
      "date": "20260701",
      "country": "fr",
      "mediaType": "apps",
      "feed": "top-paid",
      "rank": 98,
      "artistName": "Arobas Music",
      "id": "400666114",
      "name": "Guitar Pro",
      "releaseDate": "2011-01-15",
      "kind": "apps",
      "artworkUrl100": "https://is1-ssl.mzstatic.com/image/thumb/Purple221/v4/47/45/bc/4745bc73-f7c2-ebca-e567-f9613d004dcf/AppIcon-0-0-1x_U007emarketing-0-8-0-0-85-220.png/100x100bb.png",
      "genres": [
        {
          "genreId": "6011",
          "name": "Musique",
          "url": "https://itunes.apple.com/fr/genre/id6011"
        },
        {
          "genreId": "6002",
          "name": "Utilitaires",
          "url": "https://itunes.apple.com/fr/genre/id6002"
        }
      ],
      "url": "https://apps.apple.com/fr/app/guitar-pro/id400666114"
    }
  ]
}
