{
  "resultCount": 1,
  "results": [
    {
      "date": "20260406",
      "country": "cn",
      "mediaType": "apps",
      "feed": "top-paid",
      "rank": 97,
      "artistName": "光宇 张",
      "id": "657016140",
      "name": "Good Maps - 谷歌地图,离线,街景,公交,地铁,导航",
      "releaseDate": "2013-06-15",
      "kind": "apps",
      "artworkUrl100": "https://is1-ssl.mzstatic.com/image/thumb/Purple18/v4/a3/a0/62/a3a0621a-5411-12a9-e608-60cb259f7982/mzl.mbrgndsp.png/100x100bb.png",
      "genres": [
        {
          "genreId": "6010",
          "name": "导航",
          "url": "https://itunes.apple.com/cn/genre/id6010"
        },
        {
          "genreId": "6003",
          "name": "旅游",
          "url": "https://itunes.apple.com/cn/genre/id6003"
        }
      ],
      "url": "https://apps.apple.com/cn/app/good-maps-%E8%B0%B7%E6%AD%8C%E5%9C%B0%E5%9B%BE-%E7%A6%BB%E7%BA%BF-%E8%A1%97%E6%99%AF-%E5%85%AC%E4%BA%A4-%E5%9C%B0%E9%93%81-%E5%AF%BC%E8%88%AA/id657016140"
    }
  ]
}
