{
  "resultCount": 2,
  "results": [
    {
      "date": "20260406",
      "country": "us",
      "mediaType": "apps",
      "feed": "top-paid",
      "rank": 53,
      "artistName": "Seongmin Lee",
      "id": "6742218180",
      "name": "희담필터",
      "releaseDate": "2025-03-03",
      "kind": "apps",
      "artworkUrl100": "https://is1-ssl.mzstatic.com/image/thumb/Purple221/v4/e3/33/ac/e333ac36-99e5-7209-074b-563c38d7c93e/AppIcon-0-0-1x_U007epad-0-1-0-85-220.png/100x100bb.png",
      "genres": [
        {
          "genreId": "6008",
          "name": "Photo & Video",
          "url": "https://itunes.apple.com/us/genre/id6008"
        }
      ],
      "url": "https://apps.apple.com/us/app/%ED%9D%AC%EB%8B%B4%ED%95%84%ED%84%B0/id6742218180"
    },
    {
      "date": "20260601",
      "country": "us",
      "mediaType": "apps",
      "feed": "top-paid",
      "rank": 40,
      "artistName": "Seongmin Lee",
      "id": "6742218180",
      "name": "Heedam Filter",
      "releaseDate": "2025-03-03",
      "kind": "apps",
      "artworkUrl100": "https://is1-ssl.mzstatic.com/image/thumb/Purple221/v4/94/1b/ff/941bff9b-f8e1-a0ce-c8de-0116a2aef793/AppIcon-0-0-1x_U007epad-0-1-0-85-220.png/100x100bb.png",
      "genres": [
        {
          "genreId": "6008",
          "name": "Photo & Video",
          "url": "https://itunes.apple.com/us/genre/id6008"
        }
      ],
      "url": "https://apps.apple.com/us/app/heedam-filter/id6742218180"
    }
  ]
}
