{
  "resultCount": 1,
  "results": [
    {
      "date": "20260701",
      "country": "jp",
      "mediaType": "apps",
      "feed": "top-free",
      "rank": 58,
      "artistName": "Kurashiru, Inc",
      "id": "6756568932",
      "name": "うさポ by クラシル",
      "releaseDate": "2026-01-25",
      "kind": "apps",
      "artworkUrl100": "https://is1-ssl.mzstatic.com/image/thumb/Purple221/v4/76/01/e0/7601e0a2-a43c-db34-09e5-4eed17d45a88/AppIcon-0-0-1x_U007ephone-0-1-85-220.png/100x100bb.png",
      "genres": [
        {
          "genreId": "6012",
          "name": "ライフスタイル",
          "url": "https://itunes.apple.com/jp/genre/id6012"
        },
        {
          "genreId": "6016",
          "name": "エンターテインメント",
          "url": "https://itunes.apple.com/jp/genre/id6016"
        }
      ],
      "url": "https://apps.apple.com/jp/app/%E3%81%86%E3%81%95%E3%83%9D-by-%E3%82%AF%E3%83%A9%E3%82%B7%E3%83%AB/id6756568932"
    }
  ]
}
