{
  "resultCount": 1,
  "results": [
    {
      "date": "20260601",
      "country": "jp",
      "mediaType": "books",
      "feed": "top-paid",
      "rank": 83,
      "artistName": "大瀬戸陸",
      "id": "6772960001",
      "name": "ねずみの初恋(10)",
      "releaseDate": "2026-06-05",
      "kind": "books",
      "artistId": "1485708778",
      "artistUrl": "https://books.apple.com/jp/author/%E5%A4%A7%E7%80%AC%E6%88%B8%E9%99%B8/id1485708778",
      "artworkUrl100": "https://is1-ssl.mzstatic.com/image/thumb/Publication221/v4/60/49/cb/6049cb2f-0133-0a9e-1321-6460fff3b204/BT000152825701001001900206.jpg/100x142bb.png",
      "genres": [
        {
          "genreId": "50000084",
          "name": "恋愛／ロマンス",
          "url": "https://itunes.apple.com/jp/genre/id50000084"
        },
        {
          "genreId": "38",
          "name": "ブック",
          "url": "https://itunes.apple.com/jp/genre/id38"
        },
        {
          "genreId": "9026",
          "name": "マンガ／グラフィックノベル",
          "url": "https://itunes.apple.com/jp/genre/id9026"
        },
        {
          "genreId": "10016",
          "name": "マンガ",
          "url": "https://itunes.apple.com/jp/genre/id10016"
        },
        {
          "genreId": "11338",
          "name": "青年",
          "url": "https://itunes.apple.com/jp/genre/id11338"
        },
        {
          "genreId": "50000081",
          "name": "ミステリー",
          "url": "https://itunes.apple.com/jp/genre/id50000081"
        }
      ],
      "url": "https://books.apple.com/jp/book/%E3%81%AD%E3%81%9A%E3%81%BF%E3%81%AE%E5%88%9D%E6%81%8B-10/id6772960001"
    }
  ]
}
