{
  "resultCount": 1,
  "results": [
    {
      "date": "20260601",
      "country": "jp",
      "mediaType": "books",
      "feed": "top-paid",
      "rank": 78,
      "artistName": "夏川勇人",
      "id": "6773616551",
      "name": "ドラハチ(10) 電子限定描きおろし特典つき",
      "releaseDate": "2026-06-17",
      "kind": "books",
      "artistId": "1645051838",
      "artistUrl": "https://books.apple.com/jp/author/%E5%A4%8F%E5%B7%9D%E5%8B%87%E4%BA%BA/id1645051838",
      "artworkUrl100": "https://is1-ssl.mzstatic.com/image/thumb/Publication221/v4/87/85/77/8785778f-ac49-084b-ecdf-07c9ea438655/BT000135980501001001900206.jpg/100x150bb.png",
      "genres": [
        {
          "genreId": "50000087",
          "name": "スポーツ",
          "url": "https://itunes.apple.com/jp/genre/id50000087"
        },
        {
          "genreId": "38",
          "name": "ブック",
          "url": "https://itunes.apple.com/jp/genre/id38"
        },
        {
          "genreId": "9026",
          "name": "マンガ／グラフィックノベル",
          "url": "https://itunes.apple.com/jp/genre/id9026"
        },
        {
          "genreId": "10016",
          "name": "マンガ",
          "url": "https://itunes.apple.com/jp/genre/id10016"
        },
        {
          "genreId": "11337",
          "name": "少年",
          "url": "https://itunes.apple.com/jp/genre/id11337"
        }
      ],
      "url": "https://books.apple.com/jp/book/%E3%83%89%E3%83%A9%E3%83%8F%E3%83%81-10-%E9%9B%BB%E5%AD%90%E9%99%90%E5%AE%9A%E6%8F%8F%E3%81%8D%E3%81%8A%E3%82%8D%E3%81%97%E7%89%B9%E5%85%B8%E3%81%A4%E3%81%8D/id6773616551"
    }
  ]
}
