{
  "resultCount": 1,
  "results": [
    {
      "wrapperType": "audiobook",
      "artistId": 1793243016,
      "collectionId": 1793243015,
      "artistName": "深水 黎一郎",
      "collectionName": "ミステリー・アリーナ: 講談社文庫",
      "collectionCensoredName": "ミステリー・アリーナ: 講談社文庫",
      "artistViewUrl": "https://books.apple.com/jp/author/%E6%B7%B1%E6%B0%B4-%E9%BB%8E%E4%B8%80%E9%83%8E/id1793243016?uo=4",
      "collectionViewUrl": "https://books.apple.com/jp/audiobook/%E3%83%9F%E3%82%B9%E3%83%86%E3%83%AA%E3%83%BC-%E3%82%A2%E3%83%AA%E3%83%BC%E3%83%8A-%E8%AC%9B%E8%AB%87%E7%A4%BE%E6%96%87%E5%BA%AB/id1793243015?uo=4",
      "artworkUrl60": "https://is1-ssl.mzstatic.com/image/thumb/Music221/v4/13/d6/41/13d64188-6987-a0bd-33e5-49b989adf4d2/rm_image.jpg/60x60bb.jpg",
      "artworkUrl100": "https://is1-ssl.mzstatic.com/image/thumb/Music221/v4/13/d6/41/13d64188-6987-a0bd-33e5-49b989adf4d2/rm_image.jpg/100x100bb.jpg",
      "collectionPrice": 4380.0,
      "collectionExplicitness": "cleaned",
      "trackCount": 1,
      "copyright": "© 2025 Audible Studios",
      "country": "JPN",
      "currency": "JPY",
      "releaseDate": "2025-01-31T08:00:00Z",
      "primaryGenreName": "ミステリー",
      "previewUrl": "https://audio-ssl.itunes.apple.com/itunes-assets/AudioPreview221/v4/36/22/30/3622300d-03b7-ddda-902c-84159d780a58/mzaf_13337625061605656815.std.aac.p.m4a",
      "description": "連続殺人に挑むのはミステリー読みのプロたち――。15ある解決案のどれが真相か? 嵐で孤立した館で起きた殺人事件! 国民的娯楽番組「推理闘技場(ミステリー・アリーナ)」に出演したミステリー読みのプロたちが、早い者勝ちで謎解きに挑む。誰もが怪しく思える伏線に満ちた難題の答えはなんと15通り! そして番組の裏でも不穏な動きが……。多重解決の究極 にしてミステリー・ランキングを席巻した怒濤の傑作!!"
    }
  ]
}
