{
  "resultCount": 1,
  "results": [
    {
      "wrapperType": "track",
      "kind": "podcast",
      "collectionId": 1794450472,
      "trackId": 1794450472,
      "artistName": "The Bulwark",
      "collectionName": "Bulwark Takes",
      "trackName": "Bulwark Takes",
      "collectionCensoredName": "Bulwark Takes",
      "trackCensoredName": "Bulwark Takes",
      "collectionViewUrl": "https://podcasts.apple.com/us/podcast/bulwark-takes/id1794450472?uo=4",
      "feedUrl": "https://audioboom.com/channels/5149464.rss",
      "trackViewUrl": "https://podcasts.apple.com/us/podcast/bulwark-takes/id1794450472?uo=4",
      "artworkUrl30": "https://is1-ssl.mzstatic.com/image/thumb/Podcasts211/v4/04/cf/04/04cf0471-ef46-af11-9519-8f5f43a74897/mza_8455835125203898833.jpg/30x30bb.jpg",
      "artworkUrl60": "https://is1-ssl.mzstatic.com/image/thumb/Podcasts211/v4/04/cf/04/04cf0471-ef46-af11-9519-8f5f43a74897/mza_8455835125203898833.jpg/60x60bb.jpg",
      "artworkUrl100": "https://is1-ssl.mzstatic.com/image/thumb/Podcasts211/v4/04/cf/04/04cf0471-ef46-af11-9519-8f5f43a74897/mza_8455835125203898833.jpg/100x100bb.jpg",
      "collectionPrice": 0,
      "trackPrice": 0,
      "collectionHdPrice": 0,
      "releaseDate": "2026-07-18T23:45:00Z",
      "collectionExplicitness": "notExplicit",
      "trackExplicitness": "cleaned",
      "trackCount": 593,
      "trackTimeMillis": 1097,
      "country": "USA",
      "currency": "USD",
      "primaryGenreName": "Politics",
      "contentAdvisoryRating": "Clean",
      "artworkUrl600": "https://is1-ssl.mzstatic.com/image/thumb/Podcasts211/v4/04/cf/04/04cf0471-ef46-af11-9519-8f5f43a74897/mza_8455835125203898833.jpg/600x600bb.jpg",
      "genreIds": [
        "1527",
        "26",
        "1489",
        "1530"
      ],
      "genres": [
        "Politics",
        "Podcasts",
        "News",
        "News Commentary"
      ]
    }
  ]
}
