{
  "resultCount": 1,
  "results": [
    {
      "wrapperType": "audiobook",
      "artistId": 1815911466,
      "collectionId": 303779515,
      "artistName": "大和 マヤ",
      "collectionName": "女医マヤの相手の心をトリコにする心理術",
      "collectionCensoredName": "女医マヤの相手の心をトリコにする心理術",
      "artistViewUrl": "https://books.apple.com/jp/author/%E5%A4%A7%E5%92%8C-%E3%83%9E%E3%83%A4/id1815911466?uo=4",
      "collectionViewUrl": "https://books.apple.com/jp/audiobook/%E5%A5%B3%E5%8C%BB%E3%83%9E%E3%83%A4%E3%81%AE%E7%9B%B8%E6%89%8B%E3%81%AE%E5%BF%83%E3%82%92%E3%83%88%E3%83%AA%E3%82%B3%E3%81%AB%E3%81%99%E3%82%8B%E5%BF%83%E7%90%86%E8%A1%93/id303779515?uo=4",
      "artworkUrl60": "https://is1-ssl.mzstatic.com/image/thumb/Music221/v4/d8/25/c0/d825c098-3871-3218-20de-070f14d8fd61/lg_image.jpg/60x60bb.jpg",
      "artworkUrl100": "https://is1-ssl.mzstatic.com/image/thumb/Music221/v4/d8/25/c0/d825c098-3871-3218-20de-070f14d8fd61/lg_image.jpg/100x100bb.jpg",
      "collectionPrice": 1833,
      "collectionExplicitness": "cleaned",
      "trackCount": 1,
      "copyright": "© 2009 パンローリング株式会社",
      "country": "JPN",
      "currency": "JPY",
      "releaseDate": "2009-01-28T08:00:00Z",
      "primaryGenreName": "自己啓発",
      "previewUrl": "https://audio-ssl.itunes.apple.com/itunes-assets/AudioPreview221/v4/ce/72/4c/ce724c0b-67b3-91a5-1597-c1e1f25343e7/mzaf_10619638930132924933.std.aac.p.m4a",
      "description": "恋愛でも、ビジネスでも、自分の気持ちを高めて、相手の気持ちをトリコにしなければうまくいかないもの。本書では、明るくてセクシーな女医マヤ先生が、人の心をつかみ、抱きしめ、すべてがうまく回るようになる18の心理テクニックを紹介!マヤ先生は精神科医でもあり、部下である「ゆうきゆう」氏とメールマガジン「セクシー心理学」を運営。日本一の読者数15万人を誇り、2004年の「日本メルマガ大賞」にも選ばれています。この本には、あなたの気持ちを高め、そして相手の気持ちをトリコにする、「答え」があります。 私の学んできた精神医学・心理学、そして医師として活動する中で手に入れてきた技術。さらに学生の時から、ホスト・ホステスさんなど、さまざまな夜のお仕事の方たちと関わってきた中で得たテクニックを、余すところなく書いています。これを読み、覚えておくだけで、あなたは確実に色々な人の気持ちをつかみ、抱き締め、すべてがうまく回るようになるはずです。※本商品は「女医マヤの相手の心をトリコにする心理術」(海竜社刊 大和マヤ著ISBN:978-4-7593-0851-8 268頁1,470円(税込))をオーディオ化したものです。(C)2005 Maya Yamato"
    }
  ]
}
