{
  "resultCount": 1,
  "results": [
    {
      "trackCensoredName": "転生したら第七王子だったので、気ままに魔術を極めます(23)",
      "artistViewUrl": "https://books.apple.com/jp/artist/%E7%9F%B3%E6%B2%A2%E5%BA%B8%E4%BB%8B-%E8%AC%99%E8%99%9A%E3%81%AA%E3%82%B5%E3%83%BC%E3%82%AF%E3%83%AB-%E3%83%A1%E3%83%AB/1001893190?uo=4",
      "trackViewUrl": "https://books.apple.com/jp/book/%E8%BB%A2%E7%94%9F%E3%81%97%E3%81%9F%E3%82%89%E7%AC%AC%E4%B8%83%E7%8E%8B%E5%AD%90%E3%81%A0%E3%81%A3%E3%81%9F%E3%81%AE%E3%81%A7-%E6%B0%97%E3%81%BE%E3%81%BE%E3%81%AB%E9%AD%94%E8%A1%93%E3%82%92%E6%A5%B5%E3%82%81%E3%81%BE%E3%81%99-23/id6762606337?uo=4",
      "artworkUrl60": "https://is1-ssl.mzstatic.com/image/thumb/Publication211/v4/53/c7/f9/53c7f9f0-cf0c-6056-5007-98a3beb98a30/BT000086675602302301900206.jpg/60x60bb.jpg",
      "artworkUrl100": "https://is1-ssl.mzstatic.com/image/thumb/Publication211/v4/53/c7/f9/53c7f9f0-cf0c-6056-5007-98a3beb98a30/BT000086675602302301900206.jpg/100x100bb.jpg",
      "artistIds": [
        1001893190,
        1407548093,
        1108303367
      ],
      "artistId": 1001893190,
      "artistName": "石沢庸介, 謙虚なサークル & *メル*",
      "releaseDate": "2026-05-08T07:00:00Z",
      "trackName": "転生したら第七王子だったので、気ままに魔術を極めます(23)",
      "trackId": 6762606337,
      "genreIds": [
        "50000074",
        "38",
        "9026",
        "10016",
        "11345",
        "11337"
      ],
      "kind": "ebook",
      "currency": "JPY",
      "description": "マガポケセールスランキング1位の超話題作!<br />小説家になろう発!累計1800万PVの超人気作がコミカライズ!!<br />俺が興味あるのは魔術だけだ──<br />庶民の転生先は王子!? 桁外れの魔力と家柄でお気楽無双ライフ!!<br />残すは3体のダンジョンボス。ベイダー・ドーンに圧倒される軍師マルス!名無しの急襲を受けるイド!サルーム最大の危機に第七王子が遂に動く――。",
      "genres": [
        "ファンタジー",
        "ブック",
        "マンガ／グラフィックノベル",
        "マンガ",
        "異世界",
        "少年"
      ]
    }
  ]
}
