{
  "resultCount": 1,
  "results": [
    {
      "wrapperType": "track",
      "kind": "podcast",
      "collectionId": 6791393274,
      "trackId": 6791393274,
      "artistName": "TBS RADIO",
      "collectionName": "バービー×イモトアヤコの東京ホルモン娘",
      "trackName": "バービー×イモトアヤコの東京ホルモン娘",
      "collectionCensoredName": "バービー×イモトアヤコの東京ホルモン娘",
      "trackCensoredName": "バービー×イモトアヤコの東京ホルモン娘",
      "collectionViewUrl": "https://podcasts.apple.com/jp/podcast/%E3%83%90%E3%83%BC%E3%83%93%E3%83%BC-%E3%82%A4%E3%83%A2%E3%83%88%E3%82%A2%E3%83%A4%E3%82%B3%E3%81%AE%E6%9D%B1%E4%BA%AC%E3%83%9B%E3%83%AB%E3%83%A2%E3%83%B3%E5%A8%98/id6791393274?uo=4",
      "feedUrl": "https://feeds.megaphone.fm/TBS5837014314",
      "trackViewUrl": "https://podcasts.apple.com/jp/podcast/%E3%83%90%E3%83%BC%E3%83%93%E3%83%BC-%E3%82%A4%E3%83%A2%E3%83%88%E3%82%A2%E3%83%A4%E3%82%B3%E3%81%AE%E6%9D%B1%E4%BA%AC%E3%83%9B%E3%83%AB%E3%83%A2%E3%83%B3%E5%A8%98/id6791393274?uo=4",
      "artworkUrl30": "https://is1-ssl.mzstatic.com/image/thumb/Podcasts221/v4/19/6b/9d/196b9dfc-f891-6f28-745c-28be956f40ce/mza_14312035198150793751.jpg/30x30bb.jpg",
      "artworkUrl60": "https://is1-ssl.mzstatic.com/image/thumb/Podcasts221/v4/19/6b/9d/196b9dfc-f891-6f28-745c-28be956f40ce/mza_14312035198150793751.jpg/60x60bb.jpg",
      "artworkUrl100": "https://is1-ssl.mzstatic.com/image/thumb/Podcasts221/v4/19/6b/9d/196b9dfc-f891-6f28-745c-28be956f40ce/mza_14312035198150793751.jpg/100x100bb.jpg",
      "collectionPrice": 0,
      "trackPrice": 0,
      "collectionHdPrice": 0,
      "releaseDate": "2026-07-16T08:45:00Z",
      "collectionExplicitness": "notExplicit",
      "trackExplicitness": "notExplicit",
      "trackCount": 2,
      "trackTimeMillis": 1889,
      "country": "JPN",
      "currency": "JPY",
      "primaryGenreName": "キャリア",
      "artworkUrl600": "https://is1-ssl.mzstatic.com/image/thumb/Podcasts221/v4/19/6b/9d/196b9dfc-f891-6f28-745c-28be956f40ce/mza_14312035198150793751.jpg/600x600bb.jpg",
      "genreIds": [
        "1410",
        "26",
        "1321",
        "1324",
        "1302"
      ],
      "genres": [
        "キャリア",
        "ポッドキャスト",
        "ビジネス",
        "社会／文化",
        "個人ジャーナル"
      ]
    }
  ]
}
