{
  "resultCount": 1,
  "results": [
    {
      "wrapperType": "audiobook",
      "artistId": 566879234,
      "collectionId": 748114456,
      "artistName": "知里幸恵",
      "collectionName": "井田由美で聴く「アイヌ神謡集」 ラジオ日本聴く図書室シリーズvol.140",
      "collectionCensoredName": "井田由美で聴く「アイヌ神謡集」 ラジオ日本聴く図書室シリーズvol.140",
      "artistViewUrl": "https://books.apple.com/jp/author/%E7%9F%A5%E9%87%8C%E5%B9%B8%E6%81%B5/id566879234?uo=4",
      "collectionViewUrl": "https://books.apple.com/jp/audiobook/%E4%BA%95%E7%94%B0%E7%94%B1%E7%BE%8E%E3%81%A7%E8%81%B4%E3%81%8F-%E3%82%A2%E3%82%A4%E3%83%8C%E7%A5%9E%E8%AC%A1%E9%9B%86-%E3%83%A9%E3%82%B8%E3%82%AA%E6%97%A5%E6%9C%AC%E8%81%B4%E3%81%8F%E5%9B%B3%E6%9B%B8%E5%AE%A4%E3%82%B7%E3%83%AA%E3%83%BC%E3%82%BAvol-140/id748114456?uo=4",
      "artworkUrl60": "https://is1-ssl.mzstatic.com/image/thumb/Music6/v4/34/09/dc/3409dca2-16dc-b4f0-57ad-a5547d6eb4b4/itunes.jpg/60x60bb.jpg",
      "artworkUrl100": "https://is1-ssl.mzstatic.com/image/thumb/Music6/v4/34/09/dc/3409dca2-16dc-b4f0-57ad-a5547d6eb4b4/itunes.jpg/100x100bb.jpg",
      "collectionPrice": 458.0,
      "collectionExplicitness": "cleaned",
      "trackCount": 1,
      "copyright": "© 2013 ラジオ日本",
      "country": "JPN",
      "currency": "JPY",
      "releaseDate": "2013-11-22T08:00:00Z",
      "primaryGenreName": "ノンフィクション",
      "previewUrl": "https://audio-ssl.itunes.apple.com/itunes-assets/AudioPreview123/v4/91/99/d3/9199d3c8-ba7c-3b7a-8b3f-eb55f641b677/mzaf_3514867696515117735.std.aac.p.m4a",
      "description": "ラジオ日本・聴く図書室第140弾は、知里幸恵編訳の「アイヌ神謡集」。  アイヌ人の家庭に生まれ育った知里幸恵が祖母から聞いた神々の話、  「カムイユーカラ」の13編を日本語訳、編さんした。  作者の知里幸恵は言語学者・金田一京助にもその非凡の才能を認められたが、19歳という若さで世を去った。  美しく洗練された翻訳で語られるアイヌの神々の世界。  井田由美の朗読で送る。"
    }
  ]
}
